wagtail_ninja/__init__.py
wagtail_ninja/_django_ninja_patch.py
wagtail_ninja/router.py
wagtail_ninja/schema.py
wagtail_ninja/typer.py
wagtail_ninja-0.1.19.dist-info/licenses/LICENSE
wagtail_ninja-0.1.19.dist-info/METADATA
wagtail_ninja-0.1.19.dist-info/WHEEL
wagtail_ninja-0.1.19.dist-info/top_level.txt
wagtail_ninja-0.1.19.dist-info/RECORD
