Metadata-Version: 2.4
Name: wagtail-ninja
Version: 0.1.19
Summary: Ninja API for Wagtail
Requires-Python: >=3.12
License-File: LICENSE
Requires-Dist: django-ninja<=1.5.3,>=1.4.3
Dynamic: license-file
